[
    {
        "key": "dbln",
        "value": "%7B%22100068720684029%22%3A%22SMHiyV88%22%2C%2261577847444934%22%3A%22GWN0qGGR%22%2C%2261577646975376%22%3A%225k8N9S2G%22%7D",
        "domain": "facebook.com",
        "path": "/login/device-based/",
        "hostOnly": false,
        "creation": "2025-07-05T03:30:02.067Z",
        "lastAccessed": "2025-07-05T03:30:02.067Z"
    },
    {
        "key": "datr",
        "value": "Pz1ZaIVm8F7dn3VnHnTK8ykH",
        "domain": "facebook.com",
        "path": "/",
        "hostOnly": false,
        "creation": "2025-07-05T03:30:02.067Z",
        "lastAccessed": "2025-07-05T03:30:02.067Z"
    },
    {
        "key": "sb",
        "value": "Pz1ZaF9FN12FTC86n4Z_lsCU",
        "domain": "facebook.com",
        "path": "/",
        "hostOnly": false,
        "creation": "2025-07-05T03:30:02.067Z",
        "lastAccessed": "2025-07-05T03:30:02.067Z"
    },
    {
        "key": "ps_l",
        "value": "1",
        "domain": "facebook.com",
        "path": "/",
        "hostOnly": false,
        "creation": "2025-07-05T03:30:02.067Z",
        "lastAccessed": "2025-07-05T03:30:02.067Z"
    },
    {
        "key": "ps_n",
        "value": "1",
        "domain": "facebook.com",
        "path": "/",
        "hostOnly": false,
        "creation": "2025-07-05T03:30:02.067Z",
        "lastAccessed": "2025-07-05T03:30:02.067Z"
    },
    {
        "key": "locale",
        "value": "bn_IN",
        "domain": "facebook.com",
        "path": "/",
        "hostOnly": false,
        "creation": "2025-07-05T03:30:02.067Z",
        "lastAccessed": "2025-07-05T03:30:02.067Z"
    },
    {
        "key": "pas",
        "value": "61577847444934%3AXPqIwghDRK%2C100068720684029%3AH07YDN66yv%2C61577646975376%3AvC1wsz8jRX",
        "domain": "facebook.com",
        "path": "/",
        "hostOnly": false,
        "creation": "2025-07-05T03:30:02.067Z",
        "lastAccessed": "2025-07-05T03:30:02.067Z"
    },
    {
        "key": "vpd",
        "value": "v1%3B870x432x1.6687500476837158",
        "domain": "facebook.com",
        "path": "/",
        "hostOnly": false,
        "creation": "2025-07-05T03:30:02.067Z",
        "lastAccessed": "2025-07-05T03:30:02.067Z"
    },
    {
        "key": "c_user",
        "value": "61577646975376",
        "domain": "facebook.com",
        "path": "/",
        "hostOnly": false,
        "creation": "2025-07-05T03:30:02.067Z",
        "lastAccessed": "2025-07-05T03:30:02.067Z"
    },
    {
        "key": "xs",
        "value": "14%3AgyZVnkQ47pyz6Q%3A2%3A1751646063%3A-1%3A-1",
        "domain": "facebook.com",
        "path": "/",
        "hostOnly": false,
        "creation": "2025-07-05T03:30:02.067Z",
        "lastAccessed": "2025-07-05T03:30:02.068Z"
    },
    {
        "key": "fr",
        "value": "08cDan8lV3L1pdJmP.AWcExaaaVXvohMbpIjrg_bah8VdfsUXXCrOi2sSC_0WQz9EZPFA.BoWT0_..AAA.0.0.BoaJvi.AWeyOMPuQHoMth4cm-lILXQfX58",
        "domain": "facebook.com",
        "path": "/",
        "hostOnly": false,
        "creation": "2025-07-05T03:30:02.068Z",
        "lastAccessed": "2025-07-05T03:30:02.068Z"
    },
    {
        "key": "fbl_st",
        "value": "100428379%3BT%3A29194768",
        "domain": "facebook.com",
        "path": "/",
        "hostOnly": false,
        "creation": "2025-07-05T03:30:02.068Z",
        "lastAccessed": "2025-07-05T03:30:02.068Z"
    },
    {
        "key": "wl_cbv",
        "value": "v2%3Bclient_version%3A2860%3Btimestamp%3A1751686114",
        "domain": "facebook.com",
        "path": "/",
        "hostOnly": false,
        "creation": "2025-07-05T03:30:02.068Z",
        "lastAccessed": "2025-07-05T03:30:02.068Z"
    }
]
